{
  "thema": "ma-08-flaechen-und-rauminhalte",
  "hinweis": "Lernbüro-Ergänzungsaufgaben für Block 4 (Flächen- und Rauminhalte). Fachliche Prüfung ausstehend.",
  "aufgaben": [
    {
      "id": "ma-08-fl-101",
      "typ": "numerisch",
      "zweig": [
        "gym",
        "rs"
      ],
      "niveau": 3,
      "afb": 3,
      "ergaenzung": "lernbuero",
      "frage": "Ein Parallelogramm hat die Seiten $a = 10\\,\\text{cm}$ und $b = 6\\,\\text{cm}$. Der eingeschlossene Winkel beträgt $60^\\circ$. Berechne den Flächeninhalt. (Hinweis: Die Höhe zum Winkel ist $h = b \\cdot \\sin(60^\\circ) \\approx 5{,}196\\,\\text{cm}$.)",
      "eingaben": [
        {
          "label": "Flächeninhalt $A$",
          "antwort": 51.96,
          "toleranz": 0.1,
          "einheit": "cm²"
        }
      ],
      "tipps": [
        "Die Höhenh. hängt mit dem Winkel und einer Seite zusammen: $h = b \\cdot \\sin(60^\\circ)$.",
        "Berechne zuerst die Höhe: $h = 6 \\cdot \\sin(60^\\circ) \\approx 6 \\cdot 0{,}866 = 5{,}196\\,\\text{cm}$.",
        "Dann gilt $A = g \\cdot h = 10 \\cdot 5{,}196 \\approx 51{,}96\\,\\text{cm}^2$."
      ],
      "loesungsweg": "Die Höhe zum Winkel von $60^\\circ$: $h = b \\cdot \\sin(60^\\circ) = 6 \\cdot \\frac{\\sqrt{3}}{2} \\approx 5{,}196\\,\\text{cm}$. Damit $A = g \\cdot h = 10 \\cdot 5{,}196 \\approx 51{,}96\\,\\text{cm}^2$.",
      "kc": [
        "KC Mathematik Gym Sek I (2015): Laengen, Flaechen- und Rauminhalte und deren Terme (7/8)"
      ]
    },
    {
      "id": "ma-08-fl-102",
      "typ": "numerisch",
      "zweig": [
        "gym",
        "rs"
      ],
      "niveau": 3,
      "afb": 3,
      "ergaenzung": "lernbuero",
      "frage": "Ein Dreieck hat die Ecken $A(0\\,|\\,0)$, $B(8\\,|\\,0)$ und $C(3\\,|\\,5)$. Berechne den Flächeninhalt mit der Formel $A = \\frac{g \\cdot h}{2}$, wobei $g = AB$ die Grundseite ist.",
      "eingaben": [
        {
          "label": "Flächeninhalt $A$",
          "antwort": 20.0,
          "toleranz": 0.05,
          "einheit": "cm²"
        }
      ],
      "tipps": [
        "Die Grundseite $g = AB$ liegt auf der $x$-Achse. Welche Länge hat $AB$?",
        "$g = 8\\,\\text{cm}$. Die Höhe zur Grundseite $AB$ ist der senkrechte Abstand von $C$ zur $x$-Achse.",
        "Der $y$-Wert von $C$ gibt die Höhe: $h = 5\\,\\text{cm}$. Also $A = \\frac{8 \\cdot 5}{2} = 20\\,\\text{cm}^2$."
      ],
      "loesungsweg": "Grundseite $g = |AB| = 8\\,\\text{cm}$. Höhe $h$ = senkrechter Abstand von $C$ zur Grundlinie = $y_C = 5\\,\\text{cm}$. Flächeninhalt: $A = \\frac{8 \\cdot 5}{2} = 20\\,\\text{cm}^2$.",
      "kc": [
        "KC Mathematik Gym Sek I (2015): Laengen, Flaechen- und Rauminhalte und deren Terme (7/8)"
      ]
    },
    {
      "id": "ma-08-fl-103",
      "typ": "numerisch",
      "zweig": [
        "gym",
        "rs"
      ],
      "niveau": 3,
      "afb": 3,
      "ergaenzung": "lernbuero",
      "frage": "Ein Trapez hat die parallelen Seiten $a = 5\\,\\text{cm}$ und $c = 11\\,\\text{cm}$ sowie die Höhe $h = 6\\,\\text{cm}$. Berechne den Flächeninhalt.",
      "eingaben": [
        {
          "label": "Flächeninhalt $A$",
          "antwort": 48.0,
          "toleranz": 0.05,
          "einheit": "cm²"
        }
      ],
      "tipps": [
        "Die Trapezformel lautet $A = \\frac{(a + c) \\cdot h}{2}$.",
        "Setze ein: $A = \\frac{(5 + 11) \\cdot 6}{2}$.",
        "$A = \\frac{16 \\cdot 6}{2} = \\frac{96}{2} = 48\\,\\text{cm}^2$."
      ],
      "loesungsweg": "$A = \\frac{(a + c) \\cdot h}{2} = \\frac{(5 + 11) \\cdot 6}{2} = \\frac{16 \\cdot 6}{2} = \\frac{96}{2} = 48\\,\\text{cm}^2$.",
      "kc": [
        "KC Mathematik Gym Sek I (2015): Laengen, Flaechen- und Rauminhalte und deren Terme (7/8)"
      ]
    },
    {
      "id": "ma-08-fl-104",
      "typ": "numerisch",
      "zweig": [
        "gym",
        "rs"
      ],
      "niveau": 3,
      "afb": 3,
      "ergaenzung": "lernbuero",
      "frage": "Eine zusammengesetzte Fläche besteht aus einem Rechteck ($8\\,\\text{cm} \\times 5\\,\\text{cm}$) und einem darauf sitzenden gleichschenkligen Dreieck mit Basis $8\\,\\text{cm}$ und Höhe $3\\,\\text{cm}$. Berechne den Gesamtflächeninhalt.",
      "eingaben": [
        {
          "label": "Gesamtfläche $A$",
          "antwort": 52.0,
          "toleranz": 0.05,
          "einheit": "cm²"
        }
      ],
      "tipps": [
        "Berechne zuerst die Flächenteile einzeln: Rechteck und Dreieck.",
        "Rechteck: $A_R = 8 \\cdot 5 = 40\\,\\text{cm}^2$. Dreieck: $A_D = \\frac{8 \\cdot 3}{2} = 12\\,\\text{cm}^2$.",
        "Gesamtfläche: $A = 40 + 12 = 52\\,\\text{cm}^2$."
      ],
      "loesungsweg": "$A_R = 8 \\cdot 5 = 40\\,\\text{cm}^2$. $A_D = \\frac{8 \\cdot 3}{2} = 12\\,\\text{cm}^2$. Gesamt: $A = 40 + 12 = 52\\,\\text{cm}^2$.",
      "kc": [
        "KC Mathematik Gym Sek I (2015): Laengen, Flaechen- und Rauminhalte und deren Terme (7/8)"
      ]
    },
    {
      "id": "ma-08-fl-105",
      "typ": "numerisch",
      "zweig": [
        "gym",
        "rs"
      ],
      "niveau": 1,
      "afb": 1,
      "ergaenzung": "lernbuero",
      "frage": "Ein gerades Prisma hat eine rechteckige Grundfläche mit den Seiten $4\\,\\text{cm}$ und $3\\,\\text{cm}$. Die Höhe des Prismas beträgt $7\\,\\text{cm}$. Berechne das Volumen.",
      "eingaben": [
        {
          "label": "Volumen $V$",
          "antwort": 84.0,
          "toleranz": 0.05,
          "einheit": "cm³"
        }
      ],
      "tipps": [
        "Das Volumen eines Prismas berechnet man mit $V = G \\cdot h$, wobei $G$ die Grundfläche ist.",
        "Berechne zuerst die Grundfläche: $G = 4 \\cdot 3 = 12\\,\\text{cm}^2$.",
        "$V = G \\cdot h = 12 \\cdot 7 = 84\\,\\text{cm}^3$."
      ],
      "loesungsweg": "Grundfläche: $G = 4 \\cdot 3 = 12\\,\\text{cm}^2$. Volumen: $V = G \\cdot h = 12 \\cdot 7 = 84\\,\\text{cm}^3$.",
      "kc": [
        "KC Mathematik Gym Sek I (2015): Laengen, Flaechen- und Rauminhalte und deren Terme (7/8)"
      ]
    },
    {
      "id": "ma-08-fl-106",
      "typ": "numerisch",
      "zweig": [
        "gym",
        "rs"
      ],
      "niveau": 2,
      "afb": 2,
      "ergaenzung": "lernbuero",
      "frage": "Ein dreieckiges Prisma hat als Grundfläche ein rechtwinkliges Dreieck mit den Katheten $5\\,\\text{cm}$ und $4\\,\\text{cm}$. Die Prismahöhe beträgt $10\\,\\text{cm}$. Berechne das Volumen.",
      "eingaben": [
        {
          "label": "Volumen $V$",
          "antwort": 100.0,
          "toleranz": 0.05,
          "einheit": "cm³"
        }
      ],
      "tipps": [
        "Berechne zuerst die Grundfläche (das Dreieck) mit $G = \\frac{g \\cdot h_D}{2}$.",
        "$G = \\frac{5 \\cdot 4}{2} = 10\\,\\text{cm}^2$.",
        "$V = G \\cdot h = 10 \\cdot 10 = 100\\,\\text{cm}^3$."
      ],
      "loesungsweg": "Grundfläche des Dreiecks: $G = \\frac{5 \\cdot 4}{2} = 10\\,\\text{cm}^2$. Volumen: $V = G \\cdot h = 10 \\cdot 10 = 100\\,\\text{cm}^3$.",
      "kc": [
        "KC Mathematik Gym Sek I (2015): Laengen, Flaechen- und Rauminhalte und deren Terme (7/8)"
      ]
    },
    {
      "id": "ma-08-fl-107",
      "typ": "numerisch",
      "zweig": [
        "gym"
      ],
      "niveau": 3,
      "afb": 3,
      "ergaenzung": "lernbuero",
      "frage": "Ein dreieckiges Prisma hat als Grundfläche ein gleichseitiges Dreieck mit Seite $a = 6\\,\\text{cm}$. Die Prismahöhe beträgt $8\\,\\text{cm}$. Berechne das Volumen. (Hinweis: Flächeninhalt gleichseitiges Dreieck: $G = \\frac{a^2 \\cdot \\sqrt{3}}{4}$.)",
      "eingaben": [
        {
          "label": "Volumen $V$",
          "antwort": 124.71,
          "toleranz": 0.2,
          "einheit": "cm³"
        }
      ],
      "tipps": [
        "Grundfläche: $G = \\frac{6^2 \\cdot \\sqrt{3}}{4} = \\frac{36\\sqrt{3}}{4} = 9\\sqrt{3}$.",
        "$9\\sqrt{3} \\approx 9 \\cdot 1{,}732 = 15{,}588\\,\\text{cm}^2$.",
        "$V = G \\cdot h = 15{,}588 \\cdot 8 \\approx 124{,}71\\,\\text{cm}^3$."
      ],
      "loesungsweg": "$G = \\frac{6^2 \\cdot \\sqrt{3}}{4} = 9\\sqrt{3} \\approx 15{,}588\\,\\text{cm}^2$. $V = 15{,}588 \\cdot 8 \\approx 124{,}71\\,\\text{cm}^3$.",
      "kc": [
        "KC Mathematik Gym Sek I (2015): Laengen, Flaechen- und Rauminhalte und deren Terme (7/8)"
      ]
    },
    {
      "id": "ma-08-fl-108",
      "typ": "numerisch",
      "zweig": [
        "gym",
        "rs"
      ],
      "niveau": 2,
      "afb": 2,
      "ergaenzung": "lernbuero",
      "frage": "Ein Quader (rechteckiges Prisma) hat die Abmessungen $l = 5\\,\\text{cm}$, $b = 3\\,\\text{cm}$, $h = 4\\,\\text{cm}$. Berechne die Oberfläche.",
      "eingaben": [
        {
          "label": "Oberfläche $O$",
          "antwort": 94.0,
          "toleranz": 0.05,
          "einheit": "cm²"
        }
      ],
      "tipps": [
        "Die Oberfläche eines Quaders besteht aus 3 Paar Rechtecken: $O = 2(l \\cdot b + l \\cdot h + b \\cdot h)$.",
        "Berechne die drei Paare: $l \\cdot b = 15$; $l \\cdot h = 20$; $b \\cdot h = 12$.",
        "$O = 2 \\cdot (15 + 20 + 12) = 2 \\cdot 47 = 94\\,\\text{cm}^2$."
      ],
      "loesungsweg": "$O = 2(l \\cdot b + l \\cdot h + b \\cdot h) = 2(5 \\cdot 3 + 5 \\cdot 4 + 3 \\cdot 4) = 2(15 + 20 + 12) = 2 \\cdot 47 = 94\\,\\text{cm}^2$.",
      "kc": [
        "KC Mathematik Gym Sek I (2015): Laengen, Flaechen- und Rauminhalte und deren Terme (7/8)"
      ]
    }
  ]
}