{
 "id": "koerper-10",
 "titel": "Lernzirkel: Körperberechnungen",
 "fach": "mathematik",
 "intro": "An diesen Stationen erkundest du runde Körper: Zylinder, Kegel und Kugel. Du veränderst Maße, knobelst an einer Anwendung und übst. Wähle frei, womit du beginnst.",
 "stationen": [
  {
   "id": "s1",
   "nr": "1",
   "titel": "Zylinder erkunden",
   "typ": "widget",
   "typLabel": "Erkunden",
   "html": "<p>Verändere Radius und Höhe des Zylinders und beobachte, wie sich Volumen und Oberfläche ändern. Was passiert beim Verdoppeln der Höhe?</p>",
   "widget": {
    "id": "koerper",
    "params": {
     "form": "zylinder",
     "einheit": "cm",
     "rinit": 3,
     "hinit": 6,
     "rmax": 6,
     "hmax": 12
    }
   }
  },
  {
   "id": "s2",
   "nr": "2",
   "titel": "Kegel und Kugel",
   "typ": "widget",
   "typLabel": "Erkunden",
   "html": "<p>Wechsle zum Kegel und erkunde, wie sein Volumen mit dem eines gleich hohen Zylinders zusammenhängt.</p>",
   "widget": {
    "id": "koerper",
    "params": {
     "form": "kegel",
     "einheit": "cm",
     "rinit": 3,
     "hinit": 5,
     "rmax": 6,
     "hmax": 10
    }
   }
  },
  {
   "id": "s3",
   "nr": "3",
   "titel": "Knobeln: Kugel im Zylinder",
   "typ": "knobel",
   "typLabel": "Knobeln",
   "html": "<p>Eine Kugel mit Radius $r$ passt genau in einen Zylinder mit Radius $r$ und Höhe $2r$. Welcher Anteil des Zylindervolumens wird von der Kugel ausgefüllt?</p><details><summary>Lösung anzeigen</summary><div><p>Kugel: $V_{\\text{K}} = \\dfrac{4}{3}\\pi r^3$. Zylinder: $V_{\\text{Z}} = \\pi r^2 \\cdot 2r = 2\\pi r^3$.</p><p>Anteil: $\\dfrac{V_{\\text{K}}}{V_{\\text{Z}}} = \\dfrac{\\frac{4}{3}\\pi r^3}{2\\pi r^3} = \\dfrac{4}{6} = \\dfrac{2}{3}$. Die Kugel füllt genau zwei Drittel des Zylinders – das wusste schon Archimedes.</p></div></details>"
  },
  {
   "id": "s4",
   "nr": "4",
   "titel": "Üben: Volumen und Oberfläche",
   "typ": "aufgaben",
   "typLabel": "Üben",
   "html": "<p>Berechne Volumen und Oberfläche und ordne die Formeln zu.</p>",
   "quelle": "ma-10-koerperberechnungen",
   "ids": [
    "ma-10-kk-004",
    "ma-10-kk-002"
   ]
  }
 ]
}